setup.py
django_topography.egg-info/PKG-INFO
django_topography.egg-info/SOURCES.txt
django_topography.egg-info/dependency_links.txt
django_topography.egg-info/top_level.txt
topography/__init__.py
topography/models.py
topography/__pycache__/__init__.cpython-35.pyc
topography/__pycache__/models.cpython-35.pyc
topography/management/__init__.py
topography/management/__pycache__/__init__.cpython-35.pyc
topography/management/commands/__init__.py
topography/management/commands/topography.py
topography/management/commands/__pycache__/__init__.cpython-35.pyc
topography/management/commands/__pycache__/topography.cpython-35.pyc