Metadata-Version: 1.0
Name: django-topography
Version: 0.0.3
Summary: Introspects the URL structure of a Django application and produces a JSON-encoded description.
Home-page: http://www.dabapps.com
Author: DabApps
Author-email: hello@dabapps.com
License: BSD
Platform: UNKNOWN
